{
  "query": "Difference in hospital beds per 1,000 people (~2017) between the birth countries of the World Snooker champions of 2007 and 2018.",
  "nodes": [
    {
      "id": 1,
      "task": "Find the World Snooker Championship winner of 2007.",
      "agent_name": "search",
      "input": [],
      "output": [
        "winner_2007"
      ],
      "prereq": []
    },
    {
      "id": 2,
      "task": "Find the World Snooker Championship winner of 2018.",
      "agent_name": "search",
      "input": [],
      "output": [
        "winner_2018"
      ],
      "prereq": []
    },
    {
      "id": 3,
      "task": "Find the birth country of the winner_2007.",
      "agent_name": "search",
      "input": [
        {
          "variable": "winner_2007",
          "value": ""
        }
      ],
      "output": [
        "country_2007"
      ],
      "prereq": [
        1
      ]
    },
    {
      "id": 4,
      "task": "Find the birth country of the winner_2018.",
      "agent_name": "search",
      "input": [
        {
          "variable": "winner_2018",
          "value": ""
        }
      ],
      "output": [
        "country_2018"
      ],
      "prereq": [
        4
      ]
    },
    {
      "id": 5,
      "task": "Look up the number of hospital beds per 1,000 people in country_2007 around 2017 using WHO/World Bank data.",
      "agent_name": "search",
      "input": [
        {
          "variable": "country_2007",
          "value": ""
        }
      ],
      "output": [
        "beds_2007"
      ],
      "prereq": [
        2
      ]
    },
    {
      "id": 6,
      "task": "Calculate the absolute difference between beds_2007 and beds_2018.",
      "agent_name": "math",
      "input": [
        {
          "variable": "beds_2007",
          "value": ""
        },
        {
          "variable": "beds_2018",
          "value": ""
        }
      ],
      "output": [
        "absolute_difference"
      ],
      "prereq": [
        3,
        6
      ]
    }
  ],
  "edges": [
    {
      "src_node": 1,
      "dest_node": 3,
      "src_output": "winner_2007",
      "dest_input": "winner_2007"
    },
    {
      "src_node": 2,
      "dest_node": 4,
      "src_output": "winner_2018",
      "dest_input": "winner_2018"
    },
    {
      "src_node": 3,
      "dest_node": 5,
      "src_output": "country_2007",
      "dest_input": "country_2007"
    },
    {
      "src_node": 4,
      "dest_node": 6,
      "src_output": "country_2018",
      "dest_input": "beds_2018"
    },
    {
      "src_node": 5,
      "dest_node": 6,
      "src_output": "beds_2007",
      "dest_input": "beds_2007"
    }
  ]
}